<?xml version="1.0" encoding="utf-8" standalone="yes"?><ns21:ReadTripResponse xmlns:ns42="urn:expedia:om:supply:messages:defn:v1" xmlns:ns41="urn:expedia:payment:system:types:v2" xmlns:ns40="urn:expedia:e3:ss:lodging:lodginginterface:messages:purchasetypes:defn:v2" xmlns:ns46="urn:expedia:e3:ss:lodging:lodginginterface:changecommontypes:defn:v1" xmlns:ns45="urn:expedia:e3:partnerlty:sterling:types:v1" xmlns:ns44="urn:expedia:e3:cpn:domain:basetypes:defn:v2" xmlns:ns43="urn:expedia:om:supply:datatype:defn:v1" xmlns:ns49="urn:expedia:e3:lty:domain:pointbanktypes:defn:v1" xmlns:ns48="urn:expedia:payment:omsadapter:types:v1" xmlns:ns47="urn:expedia:e3:ss:lodging:lodginginterface:messages:softchangetypes:defn:v1" xmlns:ns16="urn:expedia:e3:data:revitemtypes:defn:v1" xmlns:ns17="urn:expedia:e3:data:financetypes:defn:v4" xmlns:ns14="urn:expedia:e3:ss:lodging:lodginginterface:bookingcommontypes:defn:v2" xmlns:ns15="urn:expedia:e3:ss:lodging:lodginginterface:messages:availdetailtypes:defn:v3" xmlns:ns18="urn:expedia:e3:data:airtypes:defn:v6" xmlns:ns19="urn:expedia:e3:data:ancillarytypes:defn:v2" xmlns:ns12="urn:expedia:e3:ss:lodging:lodginginterface:messages:retrievetypes:defn:v1" xmlns:ns13="urn:expedia:e3:ss:lodging:lodginginterface:commontypes:defn:v4" xmlns:ns10="urn:expedia:e3:data:persontypes:defn:v4" xmlns:ns11="urn:expedia:e3:ews:core:trip:entities:defn:v2" xmlns:ns51="urn:expedia:e3:lty:domain:commontypes:defn:v1" xmlns:ns50="urn:expedia:e3:lty:domain:adaptorproxy:defn:v1" xmlns:ns53="urn:expedia:e3:lty:domain:basetypes:defn:v1" xmlns:ns52="urn:expedia:e3:lty:domain:offertypes:defn:v1" xmlns:ns55="urn:expedia:e3:shop:presto:datatype:v1" xmlns:ns54="urn:expedia:e3:shop:packages:messages:changetypes:defn:v1" xmlns:ns57="urn:expedia:e3:cpn:domain:contentprovidertypes:defn:v1" xmlns:ns56="urn:expedia:e3:cpn:domain:activitytypes:defn:v1" xmlns:ns59="urn:expedia:e3:ews:core:messages:common:defn:v1" xmlns:ns58="urn:expedia:e3:data:messagetypes:defn:v4" xmlns:ns29="urn:expedia:e3:data:cartypes:defn:v5" xmlns:ns25="urn:expedia:e3:insurance:basetypes:v2" xmlns:ns26="urn:expedia:e3:shop:packages:messages:ordertypes:defn:v1" xmlns:ns27="urn:expedia:e3:shop:packages:messages:common:defn:v3" xmlns:ns28="urn:expedia:e3:ews:core:itinerary:producttypes:defn:v2" xmlns:ns21="urn:expedia:e3:ews:core:trip:messages:defn:v1" xmlns:ns22="urn:expedia:e3:data:naturalproducttypes:defn:v1" xmlns:ns23="urn:expedia:e3:data:traveltypes:defn:v4" xmlns:ns24="urn:expedia:e3:insurance:basetypes:v1" xmlns:ns20="urn:expedia:e3:data:naturalkeytypes:defn:v1" xmlns:ns38="urn:expedia:payment:messages:v1" xmlns:ns39="urn:expedia:e3:ss:lodging:lodginginterface:messages:preparepurchasetypes:defn:v2" xmlns:ns36="urn:expedia:om:datatype:defn:v1" xmlns:ns37="urn:com:expedia:s3:cars:data:carerrortypes:defn:v2" xmlns:ns9="urn:expedia:e3:ss:lodging:lodginginterface:messages:availdetailtypes:defn:v2" xmlns:ns34="urn:expedia:payment:processor:messages:v2" xmlns:ns35="urn:expedia:e3:data:revenueoptimizationtypes:defn:v1" xmlns:ns32="urn:expedia:om:common:defn:v1" xmlns:ns33="urn:expedia:e3:data:errortypes:defn:v4" xmlns:ns5="urn:expedia:e3:ss:lodging:lodginginterface:commontypes:defn:v3" xmlns:ns30="urn:expedia:e3:data:cruise:types:v1" xmlns:ns6="urn:expedia:e3:data:timetypes:defn:v4" xmlns:ns31="urn:expedia:s3:edx:data:edxtypes:defn:v1" xmlns:ns7="urn:expedia:e3:ss:lodging:lodginginterface:bookingcommontypes:defn:v1" xmlns:ns8="urn:expedia:e3:data:placetypes:defn:v4" xmlns:ns2="urn:expedia:e3:ews:core:trip:entities:defn:v1" xmlns:ns4="urn:expedia:e3:data:basetypes:defn:v4" xmlns:ns3="urn:expedia:e3:ews:core:itinerary:commontypes:defn:v1"><ns59:ResponseInfo><ns58:MessageInfo ns58:TransactionGUID="009f1625-01c4-4c4f-a836-614f6a3b1fdd" ns58:MessageGUID="23617cf3-8982-4d2d-9d40-339b397d7f88" ns58:MessageVersion="1.0.0" ns58:MessageNameString="com.expedia.e3.ews.core.trip.messages.defn.v1.ReadTripResponseType" ns6:CreateDateTime="2015-09-29T07:56:16.061-07:00"/><ns59:ResponseStatus><ns59:StatusCodeCategory>Success</ns59:StatusCodeCategory><ns59:StatusCodeNamespace>expedia.e3.ews.core.trip.service.v1.impl.TripService</ns59:StatusCodeNamespace><ns59:StatusCode>200</ns59:StatusCode><ns59:StatusMsg></ns59:StatusMsg></ns59:ResponseStatus></ns59:ResponseInfo><ns2:Trip><ns2:TripKey><ns2:TripID>5e0dafdd-5561-4029-82d1-166372141760</ns2:TripID><ns2:TripNumber>7834331380</ns2:TripNumber><ns3:ItineraryID><ns3:TravelRecordLocator>16242148</ns3:TravelRecordLocator><ns4:LegacySiteKey><ns4:TPID>1</ns4:TPID></ns4:LegacySiteKey><ns3:ItineraryNumber>11624214868</ns3:ItineraryNumber></ns3:ItineraryID></ns2:TripKey><ns2:Title>LX activity Saved</ns2:Title><ns2:Description></ns2:Description><ns2:LoginAccountID><ns4:UserID>4249050</ns4:UserID><ns4:SiteKey><ns4:SiteID>1</ns4:SiteID></ns4:SiteKey></ns2:LoginAccountID><ns2:AccountID><ns4:UserID>4249050</ns4:UserID><ns4:LegacySiteKey><ns4:TPID>1</ns4:TPID></ns4:LegacySiteKey></ns2:AccountID><ns2:EntityList><ns2:Entity><ns2:EntityID>25AE2A8B-4680-4A37-BE29-F9E7E03CE1FE</ns2:EntityID><ns2:Version>0</ns2:Version><ns2:MetaDataList><ns2:MetaDataElement><ns2:Authority>TRIP</ns2:Authority><ns2:Key>isE3Only</ns2:Key><ns2:Value>true</ns2:Value></ns2:MetaDataElement><ns2:MetaDataElement><ns2:Authority>TRIP</ns2:Authority><ns2:Key>TRIP_DESTINATION#TRIP_DESTINATION</ns2:Key><ns2:Value>Rome, Italy</ns2:Value></ns2:MetaDataElement></ns2:MetaDataList><ns11:DestinationExperienceProductEntity><ns31:ProductInstanceID>a4b2dfb96407cbea93fd9a48983f90b9fb0ad119</ns31:ProductInstanceID><ns31:ProductNaturalKey>{"version":"1.0","siteId":"1","locale":"en_US","category":"2","legacySkuId":"53521","legacyOfferingId":"10911","avGuestTypeLabelToBookingCodeMap":{"Adult":"417"},"isPackagePath":true,"productRequestParams":{"activityID":166587,"activityItemID":166592,"activityStartDateTimeInformation":{"date":"2015-11-29","time":"09:30:00"},"allDayActivity":false,"ticketCountsByCategoryList":{"ticketCountsByCategories":[{"ticketCategoryCode":"Adult_417","count":1}]},"productUsedWith":"STANDALONE","requestedLanguageLocale":"en_US","edxSessionDataList":{"edxSessionDatas":[{"key":"DestinationRegionID","value":"179899"}]}}}</ns31:ProductNaturalKey><ns22:TotalPrice><BasePrice><ns4:SimpleAmount>55.98</ns4:SimpleAmount><ns17:CurrencyCode>USD</ns17:CurrencyCode></BasePrice></ns22:TotalPrice><ns31:TravelerList><ns31:Traveler><ns31:IsRedeemer>false</ns31:IsRedeemer><ns23:Traveler><ns10:Person><ns10:PersonName><ns10:FirstName></ns10:FirstName><ns10:MiddleName></ns10:MiddleName><ns10:LastName></ns10:LastName></ns10:PersonName><ns10:Age><ns10:AgeCode>Adult</ns10:AgeCode></ns10:Age></ns10:Person><ns10:ContactInformation/></ns23:Traveler><ns31:FilledBookingInformationPairList><ns31:FilledBookingInformationPair><ns31:BookingInformationKey>supplierOfferId</ns31:BookingInformationKey><ns31:BookingInformationValue>166592</ns31:BookingInformationValue></ns31:FilledBookingInformationPair></ns31:FilledBookingInformationPairList></ns31:Traveler></ns31:TravelerList><ns31:ActivityStartDateTimeInformation><ns6:Date>2015-11-29T09:30:00</ns6:Date><ns6:Time>2015-11-29T09:30:00</ns6:Time></ns31:ActivityStartDateTimeInformation><ns31:ActivityEndDateTimeInformation><ns6:Date>2015-11-29T12:30:00</ns6:Date><ns6:Time>2015-11-29T12:30:00</ns6:Time></ns31:ActivityEndDateTimeInformation><ns31:AllDayActivity>false</ns31:AllDayActivity></ns11:DestinationExperienceProductEntity></ns2:Entity></ns2:EntityList><ns2:CreateDateTime>2015-09-29T14:11:45.970Z</ns2:CreateDateTime><ns2:UpdateDateTime>2015-09-29T14:46:45.797Z</ns2:UpdateDateTime><ns2:TripVersion>8</ns2:TripVersion><ns2:ClientInformation><ns2:ClientID>3</ns2:ClientID></ns2:ClientInformation></ns2:Trip><ns21:ReadTripDataDetails><ns21:FromCache>false</ns21:FromCache><ns21:LastUpdateDateTime>2015-09-29T14:56:16.232Z</ns21:LastUpdateDateTime></ns21:ReadTripDataDetails></ns21:ReadTripResponse>